juziye/__init__.py
juziye/juziye.py
juziye-4.dist-info/METADATA
juziye-4.dist-info/WHEEL
juziye-4.dist-info/top_level.txt
juziye-4.dist-info/RECORD
